xcryptowatch/__init__.py
xcryptowatch/config_json.py
xcryptowatch/core.py
xcryptowatch/gpt.py
xcryptowatch/log.py
xcryptowatch/mail.py
xcryptowatch-0.1.2.dist-info/LICENSE
xcryptowatch-0.1.2.dist-info/METADATA
xcryptowatch-0.1.2.dist-info/WHEEL
xcryptowatch-0.1.2.dist-info/entry_points.txt
xcryptowatch-0.1.2.dist-info/top_level.txt
xcryptowatch-0.1.2.dist-info/RECORD
