Metadata-Version: 2.2
Name: xcryptowatch
Version: 0.1.2
Summary: A program to monitor crypto trends on social media.
Home-page: https://github.com/steelproxy/xcryptowatch
Author: Collin Rodes
Author-email: steelproxy@protonmail.com
Classifier: Programming Language :: Python :: 3
Classifier: License :: OSI Approved :: MIT License
Classifier: Operating System :: OS Independent
Requires-Python: >=3.6
License-File: LICENSE
Requires-Dist: postalsend
Requires-Dist: jsonschema
Requires-Dist: tweepy
Requires-Dist: openai
Requires-Dist: truthbrush
Requires-Dist: atproto
Dynamic: author
Dynamic: author-email
Dynamic: classifier
Dynamic: description
Dynamic: description-content-type
Dynamic: home-page
Dynamic: requires-dist
Dynamic: requires-python
Dynamic: summary
